django_fragment_cache-0.5.1.dist-info/METADATA
django_fragment_cache-0.5.1.dist-info/RECORD
django_fragment_cache-0.5.1.dist-info/WHEEL
django_fragment_cache-0.5.1.dist-info/top_level.txt
fragment_cache/__init__.py
fragment_cache/templatetags/__init__.py
fragment_cache/templatetags/fragment_cache.py
