Metadata-Version: 2.1
Name: django-fragment-cache
Version: 0.5.1
Summary: a tag for improving django template fragment cache
Home-page: https://github.com/hongweipeng/django-fragment-cache
Author: hongweipeng
Author-email: 
License: UNKNOWN
Platform: UNKNOWN
Classifier: Programming Language :: Python :: 3
Classifier: License :: OSI Approved :: MIT License
Classifier: Operating System :: OS Independent
Requires-Dist: setuptools
Requires-Dist: django (>=2)
